README.md
setup.py
contraption/Agilent.py
contraption/Arduino.py
contraption/Instrument.py
contraption/Keithley.py
contraption/Lecroy.py
contraption/LecroyTRCReader.py
contraption/Oscilloscope.py
contraption/PowerSupply.py
contraption/__init__.py
contraption.egg-info/PKG-INFO
contraption.egg-info/SOURCES.txt
contraption.egg-info/dependency_links.txt
contraption.egg-info/requires.txt
contraption.egg-info/top_level.txt