Metadata-Version: 2.1
Name: contraption
Version: 0.0.11
Summary: pyvisa support for powersupplies DPO and DAQs (Aglient, Keithley, Tektronix, Lecroy)
Home-page: https://github.com/Tsangares/Devices
Author: William Wyatt
Author-email: wwyatt@ucsc.edu
License: UNKNOWN
Platform: UNKNOWN
Classifier: Programming Language :: Python :: 3
Classifier: License :: OSI Approved :: MIT License
